italian_holidays/__init__.py
italian_holidays/italian_holidays.py
italian_holidays-0.0.7.dist-info/licenses/LICENSE
italian_holidays-0.0.7.dist-info/METADATA
italian_holidays-0.0.7.dist-info/WHEEL
italian_holidays-0.0.7.dist-info/top_level.txt
italian_holidays-0.0.7.dist-info/RECORD
