Metadata-Version: 2.4
Name: italian-holidays
Version: 0.0.7
Summary: A simple Python helper class to determine Italian holidays with the possibility to set custom holidays.
Home-page: https://github.com/giuseppebruno/italian-holidays
Author: Giuseppe Bruno
Author-email: Giuseppe Bruno <info@gbrunodev.it>
License: MIT License
Project-URL: Homepage, https://github.com/giuseppebruno/italian-holidays
Keywords: italian,holidays
Classifier: Development Status :: 5 - Production/Stable
Classifier: Intended Audience :: Developers
Classifier: Programming Language :: Python :: 3
Classifier: Programming Language :: Python :: 3.5
Classifier: Programming Language :: Python :: 3.6
Classifier: Programming Language :: Python :: 3.7
Classifier: Programming Language :: Python :: 3.8
Classifier: Programming Language :: Python :: 3.9
Classifier: Programming Language :: Python :: 3.10
Classifier: Programming Language :: Python :: 3.11
Classifier: Programming Language :: Python :: 3.12
Classifier: Programming Language :: Python :: 3.13
Classifier: License :: OSI Approved :: MIT License
Classifier: Operating System :: OS Independent
Requires-Python: >=3
License-File: LICENSE
Dynamic: author
Dynamic: home-page
Dynamic: license-file
Dynamic: requires-python
